CHANGELOG.md
majormode/__init__.py
majormode/xebus/__init__.py
majormode/xebus/constant/__init__.py
majormode/xebus/constant/bus_route.py
majormode/xebus/constant/cico.py
majormode/xebus/constant/guardian.py
majormode/xebus/constant/idr_device.py
majormode/xebus/constant/notification.py
majormode/xebus/constant/sort_order.py
majormode/xebus/constant/team.py
majormode/xebus/constant/xebus.py
majormode/xebus/model/__init__.py
majormode/xebus/model/bus_route.py
majormode/xebus/model/cico.py
majormode/xebus/utils/__init__.py
majormode/xebus/utils/formatter.py
xebus_core_library-1.4.10.dist-info/LICENSE.md
xebus_core_library-1.4.10.dist-info/WHEEL
xebus_core_library-1.4.10.dist-info/METADATA
xebus_core_library-1.4.10.dist-info/RECORD
